sweego_api/__init__.py
sweego_api/api_client.py
sweego_api/api_response.py
sweego_api/configuration.py
sweego_api/exceptions.py
sweego_api/rest.py
sweego_api/api/__init__.py
sweego_api/api/auth_api.py
sweego_api/api/billing_api.py
sweego_api/api/channels_api.py
sweego_api/api/client_api.py
sweego_api/api/client_api_key_api.py
sweego_api/api/client_billing_api.py
sweego_api/api/client_credentials_api.py
sweego_api/api/client_domain_api.py
sweego_api/api/client_mta_server_api.py
sweego_api/api/client_sftp_server_api.py
sweego_api/api/client_template_api.py
sweego_api/api/client_template_variable_api.py
sweego_api/api/client_user_api.py
sweego_api/api/configuration_api.py
sweego_api/api/default_api.py
sweego_api/api/image_hosting_api.py
sweego_api/api/logs_api.py
sweego_api/api/mta_server_api.py
sweego_api/api/mtaip_api.py
sweego_api/api/send_api.py
sweego_api/api/sftp_server_api.py
sweego_api/api/stats_api.py
sweego_api/api/webhook_api.py
sweego_api/models/__init__.py
sweego_api/models/api_key_creation_response.py
sweego_api/models/api_key_get_response.py
sweego_api/models/api_key_list_response.py
sweego_api/models/associated_api_key.py
sweego_api/models/associated_credential.py
sweego_api/models/auth_from_api_key.py
sweego_api/models/auth_right_request_input_from_api_key.py
sweego_api/models/auth_right_request_input_from_bearer.py
sweego_api/models/base_response.py
sweego_api/models/base_response1.py
sweego_api/models/billing_client_credit_response.py
sweego_api/models/billing_country.py
sweego_api/models/billing_credit_checkout.py
sweego_api/models/billing_credit_checkout_response.py
sweego_api/models/billing_credit_type.py
sweego_api/models/billing_plan.py
sweego_api/models/billing_plan_checkout.py
sweego_api/models/billing_plan_feature_data.py
sweego_api/models/billing_plan_info.py
sweego_api/models/billing_plan_subscription_started.py
sweego_api/models/channel.py
sweego_api/models/channel_consumption_quota.py
sweego_api/models/channel_credentials.py
sweego_api-1.0.0.dist-info/METADATA
sweego_api-1.0.0.dist-info/WHEEL
sweego_api-1.0.0.dist-info/top_level.txt
sweego_api-1.0.0.dist-info/RECORD
