Metadata-Version: 2.1
Name: sweego-api
Version: 1.0.0
Summary: Sweego API
Home-page: https://learn.sweego.io/
Author: Sweego
Author-email: infra@mindbaz.com
Keywords: Sweego
Requires-Dist: urllib3 <2.1.0,>=1.25.3
Requires-Dist: python-dateutil
Requires-Dist: pydantic >=2
Requires-Dist: typing-extensions >=4.7.1
